cli.py
main.py
agents/__init__.py
agents/common/__init__.py
agents/common/base.py
agents/common/exceptions.py
agents/common/logging.py
agents/common/schema_converter.py
agents/common/tools.py
agents/common/utils.py
agents/dependency_graph/__init__.py
agents/dependency_graph/agent.py
agents/dependency_graph/model.py
api_models/__init__.py
api_models/flow_api_model.py
naive_knowledge_base-0.1.2.dist-info/licenses/LICENSE
tools/__init__.py
tools/io.py
tools/tree.py
naive_knowledge_base-0.1.2.dist-info/METADATA
naive_knowledge_base-0.1.2.dist-info/WHEEL
naive_knowledge_base-0.1.2.dist-info/entry_points.txt
naive_knowledge_base-0.1.2.dist-info/top_level.txt
naive_knowledge_base-0.1.2.dist-info/RECORD
