Metadata-Version: 2.4
Name: naive-knowledge-base
Version: 0.1.2
Summary: A dependency graph analyzer using smolagents
Home-page: https://github.com/yourusername/naive-knowledge-base
Author: Your Name
Author-email: Your Name <your.email@example.com>
License: MIT
Project-URL: Homepage, https://github.com/yourusername/naive-knowledge-base
Project-URL: Documentation, https://github.com/yourusername/naive-knowledge-base#readme
Project-URL: Repository, https://github.com/yourusername/naive-knowledge-base
Project-URL: Issues, https://github.com/yourusername/naive-knowledge-base/issues
Keywords: dependency-graph,code-analysis,smolagents,ai-agents
Classifier: Development Status :: 3 - Alpha
Classifier: Intended Audience :: Developers
Classifier: Topic :: Software Development :: Libraries :: Python Modules
Classifier: License :: OSI Approved :: MIT License
Classifier: Programming Language :: Python :: 3
Classifier: Programming Language :: Python :: 3.8
Classifier: Programming Language :: Python :: 3.9
Classifier: Programming Language :: Python :: 3.10
Classifier: Programming Language :: Python :: 3.11
Classifier: Programming Language :: Python :: 3.12
Requires-Python: >=3.8
License-File: LICENSE
Requires-Dist: annotated-types==0.7.0
Requires-Dist: anyio==4.11.0
Requires-Dist: arize-phoenix-otel==0.13.1
Requires-Dist: astroid==3.3.11
Requires-Dist: attrs==25.3.0
Requires-Dist: autopep8==2.3.2
Requires-Dist: certifi==2025.8.3
Requires-Dist: charset-normalizer==3.4.3
Requires-Dist: click==8.3.0
Requires-Dist: colorama==0.4.6
Requires-Dist: coloredlogs==15.0.1
Requires-Dist: dill==0.4.0
Requires-Dist: directory_tree==1.0.0
Requires-Dist: distro==1.9.0
Requires-Dist: emerge-viz==2.0.7
Requires-Dist: filelock==3.19.1
Requires-Dist: fsspec==2025.9.0
Requires-Dist: gitdb==4.0.12
Requires-Dist: GitPython==3.1.45
Requires-Dist: googleapis-common-protos==1.70.0
Requires-Dist: grpcio==1.75.0
Requires-Dist: h11==0.16.0
Requires-Dist: hf-xet==1.1.10
Requires-Dist: httpcore==1.0.9
Requires-Dist: httpx==0.28.1
Requires-Dist: httpx-sse==0.4.1
Requires-Dist: huggingface-hub==0.35.1
Requires-Dist: humanfriendly==10.0
Requires-Dist: idna==3.10
Requires-Dist: importlib_metadata==8.7.0
Requires-Dist: interrogate==1.7.0
Requires-Dist: isort==6.0.1
Requires-Dist: Jinja2==3.1.6
Requires-Dist: jiter==0.11.0
Requires-Dist: joblib==1.5.2
Requires-Dist: jsonschema==4.25.1
Requires-Dist: jsonschema-specifications==2025.9.1
Requires-Dist: lizard==1.17.31
Requires-Dist: markdown-it-py==4.0.0
Requires-Dist: MarkupSafe==3.0.2
Requires-Dist: mccabe==0.7.0
Requires-Dist: mcp==1.14.1
Requires-Dist: mdurl==0.1.2
Requires-Dist: networkx==3.5
Requires-Dist: numpy==2.3.3
Requires-Dist: openai==1.109.1
Requires-Dist: openinference-instrumentation==0.1.38
Requires-Dist: openinference-instrumentation-smolagents==0.1.18
Requires-Dist: openinference-semantic-conventions==0.1.21
Requires-Dist: opentelemetry-api==1.37.0
Requires-Dist: opentelemetry-exporter-otlp==1.37.0
Requires-Dist: opentelemetry-exporter-otlp-proto-common==1.37.0
Requires-Dist: opentelemetry-exporter-otlp-proto-grpc==1.37.0
Requires-Dist: opentelemetry-exporter-otlp-proto-http==1.37.0
Requires-Dist: opentelemetry-instrumentation==0.58b0
Requires-Dist: opentelemetry-proto==1.37.0
Requires-Dist: opentelemetry-sdk==1.37.0
Requires-Dist: opentelemetry-semantic-conventions==0.58b0
Requires-Dist: packaging==25.0
Requires-Dist: pathspec==0.12.1
Requires-Dist: pillow==11.3.0
Requires-Dist: platformdirs==4.4.0
Requires-Dist: prettytable==3.16.0
Requires-Dist: protobuf==6.32.1
Requires-Dist: py==1.11.0
Requires-Dist: pycodestyle==2.14.0
Requires-Dist: pydantic==2.11.9
Requires-Dist: pydantic-settings==2.11.0
Requires-Dist: pydantic_core==2.33.2
Requires-Dist: PyDriller==2.9
Requires-Dist: Pygments==2.19.2
Requires-Dist: pylint==3.3.8
Requires-Dist: pyparsing==3.2.5
Requires-Dist: pyperclip==1.10.0
Requires-Dist: python-dotenv==1.1.1
Requires-Dist: python-louvain==0.16
Requires-Dist: python-multipart==0.0.20
Requires-Dist: python-sonarqube-api==2.0.5
Requires-Dist: pytz==2025.2
Requires-Dist: PyYAML==6.0.2
Requires-Dist: referencing==0.36.2
Requires-Dist: requests==2.32.5
Requires-Dist: rich==14.1.0
Requires-Dist: rpds-py==0.27.1
Requires-Dist: scikit-learn==1.7.2
Requires-Dist: scipy==1.16.2
Requires-Dist: setuptools==80.9.0
Requires-Dist: smmap==5.0.2
Requires-Dist: smolagents==1.16.1
Requires-Dist: sniffio==1.3.1
Requires-Dist: sse-starlette==3.0.2
Requires-Dist: starlette==0.48.0
Requires-Dist: tabulate==0.9.0
Requires-Dist: threadpoolctl==3.6.0
Requires-Dist: tomlkit==0.13.3
Requires-Dist: python-toon==0.1.3
Requires-Dist: tqdm==4.67.1
Requires-Dist: types-pytz==2025.2.0.20250809
Requires-Dist: typing-inspection==0.4.1
Requires-Dist: typing_extensions==4.15.0
Requires-Dist: urllib3==2.5.0
Requires-Dist: uvicorn==0.37.0
Requires-Dist: wcwidth==0.2.14
Requires-Dist: wheel==0.45.1
Requires-Dist: wrapt==1.17.3
Requires-Dist: zipp==3.23.0
Provides-Extra: dev
Requires-Dist: pytest>=7.0.0; extra == "dev"
Requires-Dist: pytest-cov>=4.0.0; extra == "dev"
Requires-Dist: black>=22.0.0; extra == "dev"
Requires-Dist: isort>=5.10.0; extra == "dev"
Requires-Dist: mypy>=1.0.0; extra == "dev"
Requires-Dist: pre-commit>=2.20.0; extra == "dev"
Dynamic: author
Dynamic: home-page
Dynamic: license-file
Dynamic: requires-python
